mathjspy/__init__.py
mathjspy/constants.py
mathjspy/mathjs.py
mathjspy-0.1.0.dist-info/METADATA
mathjspy-0.1.0.dist-info/WHEEL
mathjspy-0.1.0.dist-info/top_level.txt
mathjspy-0.1.0.dist-info/RECORD
